{
  "sentences": [
    {
      "id": "SentenceId-1",
      "type": "quicks",
      "subType": "conjunctions",
      "createdDate": "2023-06-11T00:00:00.000Z",
      "usageCount": 0,
      "isFavourite": false,
      "isUserAdded": false,
      "isBackedUp": false,
      "languageIds": ["LanguageId-1"],
      "wordIds": [
        "WordId-1","WordId-2"
      ],
      "extraRelatedWordIds": ["WordId-4", "WordId-5", "WordId-14", "WordId-19", "WordId-33"]
    },
    {
      "id": "SentenceId-2",
      "createdDate": "2023-06-11T00:00:00.000Z",
      "type": "quicks",
      "subType": "conjunctions",
      "usageCount": 0,
      "isFavourite": false,
      "isUserAdded": false,
      "isBackedUp": false,
      "languageIds": ["LanguageId-1"],
      "wordIds": [
        "WordId-1","WordId-2","WordId-3","WordId-4","WordId-5"
      ],
      "extraRelatedWordIds": ["WordId-4", "WordId-5", "WordId-14", "WordId-19", "WordId-33"]
    },
    {
      "id": "SentenceId-3",
      "createdDate": "2023-06-11T00:00:00.000Z",
      "type": "quicks",
      "subType": "conjunctions",
      "usageCount": 0,
      "isFavourite": false,
      "isUserAdded": false,
      "isBackedUp": false,
      "languageIds": ["LanguageId-1"],
      "wordIds": [
        "WordId-1","WordId-2","WordId-3"
      ],
      "extraRelatedWordIds": ["WordId-4", "WordId-5", "WordId-14", "WordId-19", "WordId-33"]
    }
  ]
}